{
"map":"far",
"name":"Persian Standard Keyboard Layout",
"mods":[0,2],
"keys":{
"04":["ش","ؤ"],
"05":["ذ"],
"06":["ز","ژ"],
"07":["ی","ي"],
"08":["ث","ٍ"],
"09":["ب","إ"],
"0a":["ل","أ"],
"0b":["ا","آ"],
"0c":["ه","ّ"],
"0d":["ت","ة"],
"0e":["ن","»"],
"0f":["م","«"],
"10":["پ","ء"],
"11":["د","ٔ"],
"12":["خ","]"],
"13":["ح","["],
"14":["ض","ْ"],
"15":["ق","ً"],
"16":["س","ئ"],
"17":["ف","ُ"],
"18":["ع","َ"],
"19":["ر","ٰ"],
"1a":["ص","ٌ"],
"1b":["ط","ط"],
"1c":["غ","ِ"],
"1d":["ظ","ك"],
"1e":["۱","!"],
"1f":["۲","٬"],
"20":["۳","٫"],
"21":["۴"],
"22":["۵","٪"],
"23":["۶","×"],
"24":["۷","،"],
"25":["۸","*"],
"26":["۹",")"],
"27":["۰","("],
"2d":["-","ـ"],
"2e":["=","+"],
"2f":["ج","}"],
"30":["چ","{"],
"31":["\\","|"],
"33":["ک",":"],
"34":["گ","؛"],
"36":["و",">"],
"37":[".","<"],
"38":["/","؟"],
"64":["\\","|"]
}
}